pytorch_rocm_gtt/VERSION
pytorch_rocm_gtt/__init__.py
pytorch_rocm_gtt/gttalloc.c
pytorch_rocm_gtt-0.1.4.dist-info/LICENSE
pytorch_rocm_gtt-0.1.4.dist-info/METADATA
pytorch_rocm_gtt-0.1.4.dist-info/WHEEL
pytorch_rocm_gtt-0.1.4.dist-info/entry_points.txt
pytorch_rocm_gtt-0.1.4.dist-info/RECORD
