Metadata-Version: 2.1
Name: pytorch-rocm-gtt
Version: 0.1.4
Summary: A memory allocator for PyTorch to allow using more memory than the iGPU reserved
Author: rochacbruno
Requires-Python: >=3.9,<4.0
Classifier: Programming Language :: Python :: 3
Classifier: Programming Language :: Python :: 3.9
Classifier: Programming Language :: Python :: 3.10
Classifier: Programming Language :: Python :: 3.11
Classifier: Programming Language :: Python :: 3.12
Project-URL: repository, https://github.com/pappacena/pytorch-rocm-gtt
